ncsim/__init__.py
ncsim/sims.py
ncsim/utils.py
ncsim-0.0.2.dist-info/METADATA
ncsim-0.0.2.dist-info/WHEEL
ncsim-0.0.2.dist-info/top_level.txt
ncsim-0.0.2.dist-info/RECORD
